vsutillib/macos/__init__.py
vsutillib/macos/utils.py
vsutillib_macos-1.6.1.dist-info/AUTHORS
vsutillib_macos-1.6.1.dist-info/LICENSE.txt
vsutillib_macos-1.6.1.dist-info/METADATA
vsutillib_macos-1.6.1.dist-info/WHEEL
vsutillib_macos-1.6.1.dist-info/top_level.txt
vsutillib_macos-1.6.1.dist-info/RECORD
