Metadata-Version: 2.1
Name: vsutillib-macos
Version: 1.6.1
Summary: vsutillib.macos sub package part of vsutillib
Home-page: https://pypi.org/project/vsutillib-macos/
Author: Efrain Vergara
Author-email: akai10tsuki@gmail.com
License: MIT
Platform: UNKNOWN
Requires-Python: >=3.8.1, <3.9
Requires-Dist: vsutillib-process (>=1.6.0)
